setup.py
fcompop/__init__.py
fcompop/core.py
fcompop.egg-info/PKG-INFO
fcompop.egg-info/SOURCES.txt
fcompop.egg-info/dependency_links.txt
fcompop.egg-info/top_level.txt