Metadata-Version: 1.1
Name: fcompop
Version: 0.3
Summary: Function composition operators for functional programming
Home-page: https://github.com/jnamika/fcompop
Author: Jun Namikawa
Author-email: jnamika@gmail.com
License: ISC License (ISCL)
Keywords: function composition operator functional programming
Platform: UNKNOWN
Classifier: Development Status :: 3 - Alpha
Classifier: Intended Audience :: Developers
Classifier: License :: OSI Approved :: ISC License (ISCL)
Classifier: Operating System :: OS Independent
Classifier: Programming Language :: Python
Classifier: Programming Language :: Python :: 2
Classifier: Programming Language :: Python :: 2.7
Classifier: Programming Language :: Python :: 3
Classifier: Programming Language :: Python :: 3.2
Classifier: Programming Language :: Python :: 3.3
Classifier: Programming Language :: Python :: 3.4
Classifier: Topic :: Software Development :: Libraries :: Python Modules
